pythonate/__init__.py
pythonate/checks.py
pythonate/dictionaries.py
pythonate/enums.py
pythonate/files.py
pythonate/json.py
pythonate/logs.py
pythonate/objects.py
pythonate/random.py
pythonate/selector.py
pythonate/sorting.py
pythonate/time.py
pythonate/uuid.py
pythonate/conversions/__init__.py
pythonate/conversions/international.py
pythonate/conversions/storage.py
pythonate/conversions/temperature.py
pythonate/data/__init__.py
pythonate/data/sql.py
pythonate/internal/__init__.py
pythonate/internal/errors.py
pythonate/security/__init__.py
pythonate/security/encryption.py
pythonate/security/gpg.py
pythonate/system/__init__.py
pythonate/system/os.py
pythonate/system/stats.py
pythonate/web/__init__.py
pythonate/web/analytics.py
pythonate/web/pastebin.py
pythonate/web/requests.py
pythonate-0.3.0.dist-info/METADATA
pythonate-0.3.0.dist-info/WHEEL
pythonate-0.3.0.dist-info/top_level.txt
pythonate-0.3.0.dist-info/RECORD
